prettylogger_8au/__init__.py
prettylogger_8au/main.py
prettylogger_8au-0.0.1.dist-info/METADATA
prettylogger_8au-0.0.1.dist-info/WHEEL
prettylogger_8au-0.0.1.dist-info/licenses/LICENSE
prettylogger_8au-0.0.1.dist-info/RECORD
