Metadata-Version: 2.1
Name: PrettyLogger_8au
Version: 0.0.1
Summary: A python libary to make pretty print() statements
Project-URL: Homepage, https://github.com/8auu/PrettyLogger
Project-URL: Bug Tracker, https://github.com/8auu/PrettyLogger/issues
Author: 8au
License: Copyright (c) 2018 The Python Packaging Authority
Classifier: License :: OSI Approved :: MIT License
Classifier: Operating System :: OS Independent
Classifier: Programming Language :: Python :: 3
Requires-Python: >=3.7
